<?xml version='1.0' encoding='utf-8'?>
<logs><log><timestamp>2025-10-18T11:00:00</timestamp><severity>DEBUG</severity><service>AuthService</service><message>Sample log message</message></log><log><timestamp>2025-10-18T11:10:00</timestamp><severity>DEBUG</severity><service>AuthService</service><message>Sample log message</message></log><log><timestamp>2025-10-18T11:20:00</timestamp><severity>WARNING</severity><service>NotificationService</service><message>Sample log message</message></log><log><timestamp>INVALID_TIMESTAMP</timestamp><severity>ERROR</severity><service>OrderService</service><message>Corrupted timestamp</message></log><log><timestamp>2025-10-18T11:40:00</timestamp><severity>WARNING</severity><service>InventoryService</service><message /></log><log><timestamp>2025-10-18T11:50:00</timestamp><severity>INFO</severity><service>OrderService</service><message>Sample log message</message></log><log><timestamp>2025-10-18T12:00:00</timestamp><severity>WARNING</severity><service>OrderService</service><message>Sample log message</message></log><log><timestamp>2025-10-18T12:10:00</timestamp><severity>CRITICAL</severity><service>InventoryService</service><message>Sample log message</message></log><log><timestamp>2025-10-18T12:20:00</timestamp><severity>DEBUG</severity><service>OrderService</service><message>Sample log message</message></log><log><timestamp>2025-10-18T12:30:00</timestamp><severity>ERROR</severity><service>OrderService</service><message>Sample log message</message></log><log><timestamp>2025-10-18T12:40:00</timestamp><severity>INFO</severity><service>NotificationService</service><message>Sample log message</message></log><log><timestamp>INVALID_TIMESTAMP</timestamp><severity>ERROR</severity><service>OrderService</service><message>Corrupted timestamp</message></log><log><timestamp>INVALID_TIMESTAMP</timestamp><severity>ERROR</severity><service>OrderService</service><message>Corrupted timestamp</message></log><log><timestamp>2025-10-18T13:10:00</timestamp><severity>ERROR</severity><service>OrderService</service><message>Sample log message</message></log><log><timestamp>2025-10-18T13:20:00</timestamp><severity>INFO</severity><service>PaymentService</service><message>Sample log message</message></log><log><timestamp>2025-10-18T13:30:00</timestamp><severity>INFO</severity><service>NotificationService</service><message>Sample log message</message></log><log><timestamp>2025-10-18T13:40:00</timestamp><severity>INFO</severity><service>PaymentService</service><message>Sample log message</message></log><log>&lt;broken&gt;&lt;log&gt;&lt;/broken&gt;</log><log><timestamp>2025-10-18T14:00:00</timestamp><severity>INFO</severity><service>InventoryService</service><message>Sample log message</message></log><log><timestamp>INVALID_TIMESTAMP</timestamp><severity>ERROR</severity><service>OrderService</service><message>Corrupted timestamp</message></log><log><timestamp>2025-10-18T14:20:00</timestamp><severity>WARNING</severity><service>NotificationService</service><message>Sample log message</message></log><log><timestamp>2025-10-18T14:30:00</timestamp><severity>DEBUG</severity><service>InventoryService</service><message>Sample log message</message></log><log><timestamp>2025-10-18T14:40:00</timestamp><severity>WARNING</severity><service>NotificationService</service><message>Sample log message</message></log><log><timestamp>2025-10-18T14:50:00</timestamp><severity>UNKNOWN</severity><service>AuthService</service><message>Invalid severity</message></log><log><timestamp>2025-10-18T15:00:00</timestamp><severity>INFO</severity><service>OrderService</service><message>Sample log message</message></log></logs>